rest_client/__init__.py
rest_client/__version__.py
rest_client/log_config.py
rest_client/base/__init__.py
rest_client/base/authentication.py
rest_client/base/client.py
rest_client/base/config.py
rest_client/base/exceptions.py
rest_client/base/util.py
rest_client/base/variables.py
rapid_rest_client-0.0.5.dist-info/LICENSE
rapid_rest_client-0.0.5.dist-info/METADATA
rapid_rest_client-0.0.5.dist-info/WHEEL
rapid_rest_client-0.0.5.dist-info/top_level.txt
rapid_rest_client-0.0.5.dist-info/RECORD
