Metadata-Version: 2.1
Name: rapid-rest-client
Version: 0.0.5
Summary: API Client
Home-page: 
Author: Michael Primke
Author-email: michael@saleweaver.com
License: MIT
License-File: LICENSE
Requires-Dist: requests
Requires-Dist: colorlog
